price_onixcoin/__init__.py
price_onixcoin/admin.py
price_onixcoin/apps.py
price_onixcoin/models.py
price_onixcoin/tests.py
price_onixcoin/views.py
price_onixcoin/management/__init__.py
price_onixcoin/management/commands/__init__.py
price_onixcoin/management/commands/price_btc_localbitcoin.py
price_onixcoin/management/commands/price_onix.py
price_onixcoin/management/commands/yobit_onix.py
price_onixcoin/migrations/0001_initial.py
price_onixcoin/migrations/0002_country.py
price_onixcoin/migrations/0003_pricebtclocalbitcoin_country.py
price_onixcoin/migrations/0004_auto_20181007_2220.py
price_onixcoin/migrations/__init__.py
price_onixcoin-0.1.1.dist-info/METADATA
price_onixcoin-0.1.1.dist-info/RECORD
price_onixcoin-0.1.1.dist-info/WHEEL
price_onixcoin-0.1.1.dist-info/top_level.txt
