Metadata-Version: 2.1
Name: price-onixcoin
Version: 0.1.1
Summary: Aplicación django para calcular el precio en Bs y USD de la criptomoneda onixcoin.
Home-page: https://github.com/abejarano/onix_price_buy
Author: abejarano
Author-email: programador.angel@gmail.com
License: BSD License
Platform: UNKNOWN
Classifier: Environment :: Web Environment
Classifier: Framework :: Django
Classifier: Intended Audience :: Developers
Classifier: License :: OSI Approved :: BSD License
Classifier: Operating System :: OS Independent
Classifier: Programming Language :: Python
Classifier: Programming Language :: Python :: 3.5
Classifier: Programming Language :: Python :: 3.6
Classifier: Topic :: Internet :: WWW/HTTP
Classifier: Topic :: Internet :: WWW/HTTP :: Dynamic Content
